{"is_source_file": false, "format": "", "description": "", "external_files": [], "external_methods": [], "published": [], "classes": [], "methods": [], "calls": [], "search-terms": [], "state": 2, "file_id": 12, "knowledge_revision": 22, "git_revision": "628bf8b7aa0668d1059181ce133a647ae2d7b28b", "hash": "3e02c79086355b966d1d96fe44d62b01", "format-version": 4, "code-base-name": "tic_tac_toe_frontend", "filename": "README.md", "revision_history": [{"22": "628bf8b7aa0668d1059181ce133a647ae2d7b28b"}]}